{"nodes": [{"id": "doc:content/zh/projects/metc.md", "label": "\u667a\u6167\u6d88\u9632\u7cfb\u7d71", "file_type": "document", "source_file": "content/zh/projects/metc.md", "source_location": "1-62", "source_url": null, "captured_at": "2026-05-20", "author": "Andy", "contributor": "Codex"}, {"id": "rat:iot-disaster-response", "label": "IoT \u793e\u5340\u9632\u707d\u8207\u6d88\u9632\u61c9\u8b8a", "file_type": "rationale", "source_file": "content/zh/projects/metc.md", "source_location": "22-26,38-43,48-61", "source_url": null, "captured_at": "2026-05-20", "author": "Andy", "contributor": "Codex"}], "edges": [{"source": "doc:content/zh/projects/metc.md", "target": "rat:iot-disaster-response", "relation": "rationale_for", "confidence": "EXTRACTED", "confidence_score": 0.99, "source_file": "content/zh/projects/metc.md", "source_location": "22-26,38-43,48-61", "weight": 1}, {"source": "doc:content/zh/projects/metc.md", "target": "doc:content/zh/projects/ti-ho-healthcare.md", "relation": "semantically_similar_to", "confidence": "INFERRED", "confidence_score": 0.8, "source_file": "content/zh/projects/metc.md", "source_location": "10-11,55-61", "weight": 0.77}], "hyperedges": []}